lexoffice/__init__.py
lexoffice/lexoffice.py
lexoffice-0.0.1.dist-info/AUTHORS.rst
lexoffice-0.0.1.dist-info/LICENSE
lexoffice-0.0.1.dist-info/METADATA
lexoffice-0.0.1.dist-info/WHEEL
lexoffice-0.0.1.dist-info/top_level.txt
lexoffice-0.0.1.dist-info/RECORD
