Metadata-Version: 2.1
Name: lexoffice
Version: 0.0.1
Summary: A Python library for interacting with the lexoffice Public API
Home-page: https://github.com/schaenzer/python-lexoffice
Author: Vincent Schänzer
Author-email: vincent@schaenzer.com
License: MIT license
Keywords: lexoffice
Platform: UNKNOWN
Classifier: Development Status :: 2 - Pre-Alpha
Classifier: Intended Audience :: Developers
Classifier: License :: OSI Approved :: MIT License
Classifier: Natural Language :: English
Classifier: Programming Language :: Python :: 2
Classifier: Programming Language :: Python :: 2.7
Classifier: Programming Language :: Python :: 3
Classifier: Programming Language :: Python :: 3.5
Classifier: Programming Language :: Python :: 3.6
Classifier: Programming Language :: Python :: 3.7
Classifier: Programming Language :: Python :: 3.8
Requires-Python: >=2.7, !=3.0.*, !=3.1.*, !=3.2.*, !=3.3.*, !=3.4.*
